akm/__init__.py
akm/akm.py
akm-1.3.5.dist-info/METADATA
akm-1.3.5.dist-info/WHEEL
akm-1.3.5.dist-info/top_level.txt
akm-1.3.5.dist-info/RECORD
